pod_store/__init__.py
pod_store/__main__.py
pod_store/episodes.py
pod_store/exc.py
pod_store/podcasts.py
pod_store/store.py
pod_store/store_file_handlers.py
pod_store/util.py
pod_store/commands/__init__.py
pod_store/commands/commit_messages.py
pod_store/commands/decorators.py
pod_store/commands/filtering.py
pod_store/commands/helpers.py
pod_store/commands/listing.py
pod_store/commands/tagging.py
pod_store-0.1.6.dist-info/LICENSE
pod_store-0.1.6.dist-info/METADATA
pod_store-0.1.6.dist-info/WHEEL
pod_store-0.1.6.dist-info/entry_points.txt
pod_store-0.1.6.dist-info/top_level.txt
pod_store-0.1.6.dist-info/RECORD
