Metadata-Version: 2.1
Name: pod-store
Version: 0.1.6
Summary: Podcast tracking client that allows syncing across devices using `git`. Inspired by the `pass` password manager.
Home-page: https://github.com/psbleep/pod-store
Author: Patrick Schneeweis
Author-email: psbleep@protonmail.com
License: GPLv3+
Keywords: podcast,podcasts,git,cli,terminal
Platform: any
Classifier: Development Status :: 3 - Alpha
Classifier: Environment :: Console
Classifier: Intended Audience :: Developers
Classifier: License :: OSI Approved
Classifier: License :: OSI Approved :: GNU General Public License v3 (GPLv3)
Classifier: Natural Language :: English
Classifier: Operating System :: POSIX
Classifier: Operating System :: POSIX :: Linux
Classifier: Programming Language :: Python
Classifier: Programming Language :: Python :: 3
Classifier: Programming Language :: Python :: 3 :: Only
Classifier: Programming Language :: Python :: 3.7
Classifier: Programming Language :: Python :: 3.8
Classifier: Programming Language :: Python :: 3.9
Classifier: Programming Language :: Python :: 3.10
Requires-Python: >=3.7
License-File: LICENSE
Requires-Dist: click (==8.0.1)
Requires-Dist: feedparser (==6.0.8)
Requires-Dist: music-tag (==0.4.3)
Requires-Dist: requests (==2.26.0)
